DrAdm1
doc
