Metadata-Version: 1.0
Name: DrAdm
Version: 1-0.3.3-alpha
Summary: This is a pack of unix utilities for handling some administrative tasks. In development.
Home-page: http://dradm.org
Author: Axel
Author-email: dev@dradm.org
License: GPL v3
Platform: UNKNOWN
Classifier: License :: OSI Approved :: GNU General Public License (GPL)
Classifier: Operating System :: Unix
Classifier: Operating System :: POSIX
Classifier: Environment :: Console
Classifier: Programming Language :: Python :: 2.6
Classifier: Programming Language :: Unix Shell
Classifier: Development Status :: 3 - Alpha
Classifier: Topic :: Utilities
Classifier: Topic :: System :: Systems Administration
Classifier: Topic :: System :: Installation/Setup
Classifier: Topic :: System :: Archiving :: Backup
Classifier: Natural Language :: English
Classifier: Natural Language :: Russian
